rjango/__init__.py
rjango/rest/__init__.py
rjango.rest-0.1.0.dist-info/METADATA
rjango.rest-0.1.0.dist-info/WHEEL
rjango.rest-0.1.0.dist-info/top_level.txt
rjango.rest-0.1.0.dist-info/RECORD
